{
  "updated_at": "2026-03-31",
  "source": "physionomie_boursiere_20260331.pdf",
  "count": 76,
  "prices": {
    "TUNINDEX": 15584.07,
    "BIAT": 142.49,
    "ATTIJARI BANK": 73.0,
    "AMEN BANK": 60.39,
    "BT": 6.74,
    "BNA": 14.6,
    "UIB": 27.05,
    "UBCI": 36.39,
    "STB": 4.2,
    "BH BANK": 10.3,
    "ATB": 3.84,
    "WIFACK INT BANK": 7.79,
    "BTE": 5.25,
    "POULINA GP HOLDING": 22.99,
    "SFBT": 14.5,
    "DELICE HOLDING": 16.2,
    "LAND'OR": 15.6,
    "ENNAKL AUTOMOBILES": 18.7,
    "ARTES": 12.99,
    "CITY CARS": 23.0,
    "MONOPRIX": 9.48,
    "SMART TUNISIE": 20.0,
    "MAGASIN GENERAL": 10.82,
    "SOTUMAG": 10.0,
    "STA": 61.0,
    "UADH": 0.43,
    "CELLCOM": 2.66,
    "BNA ASSURANCES": 280.86,
    "STAR": 64.05,
    "ASTREE": 54.0,
    "ASSUR MAGHREBIA": 72.0,
    "TUNIS RE": 13.37,
    "ASSU MAGHREBIA VIE": 8.74,
    "BH ASSURANCE": 65.5,
    "SPDIT-SICAF": 14.3,
    "TUNISIE LEASING F": 35.03,
    "ATL": 8.24,
    "CIL": 34.25,
    "ATTIJARI LEASING": 35.0,
    "HANNIBAL LEASE": 7.5,
    "BEST LEASE": 2.31,
    "PLAC. TSIE-SICAF": 41.81,
    "TUNINVEST-SICAR": 41.49,
    "BH LEASING": 3.62,
    "ONE TECH HOLDING": 9.55,
    "SOTUVER": 17.58,
    "SIAME": 3.07,
    "SAH": 13.7,
    "EURO-CYCLES": 11.5,
    "ATELIER MEUBLE INT": 4.79,
    "OFFICEPLAST": 1.94,
    "NEW BODY LINE": 3.9,
    "CARTHAGE CEMENT": 1.96,
    "MPBS": 8.2,
    "SOTEMAIL": 3.0,
    "SITS": 3.88,
    "SIMPAR": 34.4,
    "CIMENTS DE BIZERTE": 0.65,
    "SOMOCER": 0.68,
    "ESSOUKNA": 3.79,
    "SANIMED": 0.69,
    "TPR": 13.75,
    "SOTIPAPIER": 2.55,
    "AIR LIQUIDE TSIE": 183.0,
    "ICF": 91.27,
    "ALKIMIA": 12.8,
    "UNIMED": 8.49,
    "SIPHAT": 4.45,
    "TAWASOL GP HOLDING": 0.81,
    "SOTETEL": 6.86,
    "SOTRAPIL": 27.8,
    "ASSAD": 3.23,
    "STIP": 8.8,
    "TELNET HOLDING": 8.19,
    "AETECH": 0.41,
    "TUNISAIR": 0.34
  },
  "variations": {
    "BIAT": 0.42,
    "ATTIJARI BANK": -1.34,
    "AMEN BANK": -0.17,
    "BT": -2.03,
    "BNA": -2.67,
    "UIB": 0.78,
    "UBCI": -4.49,
    "STB": -1.18,
    "BH BANK": -0.39,
    "ATB": 3.23,
    "WIFACK INT BANK": -0.13,
    "BTE": -4.02,
    "POULINA GP HOLDING": 0.39,
    "SFBT": 3.94,
    "DELICE HOLDING": 0.62,
    "LAND'OR": -0.64,
    "ENNAKL AUTOMOBILES": -1.32,
    "ARTES": -3.64,
    "CITY CARS": -4.76,
    "MONOPRIX": 4.41,
    "SMART TUNISIE": 0.05,
    "MAGASIN GENERAL": 0.0,
    "SOTUMAG": -2.15,
    "STA": -0.81,
    "UADH": 0.0,
    "CELLCOM": -1.48,
    "BNA ASSURANCES": -10.51,
    "STAR": -0.96,
    "ASTREE": 0.0,
    "ASSUR MAGHREBIA": -2.57,
    "TUNIS RE": -4.43,
    "ASSU MAGHREBIA VIE": -0.11,
    "BH ASSURANCE": 0.0,
    "SPDIT-SICAF": 0.7,
    "TUNISIE LEASING F": -5.98,
    "ATL": 0.49,
    "CIL": 0.0,
    "ATTIJARI LEASING": 0.0,
    "HANNIBAL LEASE": 3.45,
    "BEST LEASE": 0.43,
    "PLAC. TSIE-SICAF": 0.0,
    "TUNINVEST-SICAR": 1.2,
    "BH LEASING": -3.21,
    "ONE TECH HOLDING": 2.69,
    "SOTUVER": 3.41,
    "SIAME": -0.97,
    "SAH": -0.29,
    "EURO-CYCLES": 1.32,
    "ATELIER MEUBLE INT": -2.04,
    "OFFICEPLAST": -1.02,
    "NEW BODY LINE": -1.27,
    "CARTHAGE CEMENT": -1.01,
    "MPBS": 0.0,
    "SOTEMAIL": 0.0,
    "SITS": 0.0,
    "SIMPAR": 0.0,
    "CIMENTS DE BIZERTE": 3.17,
    "SOMOCER": 3.03,
    "ESSOUKNA": 3.27,
    "SANIMED": -4.17,
    "TPR": -1.72,
    "SOTIPAPIER": 0.0,
    "AIR LIQUIDE TSIE": 0.55,
    "ICF": -1.86,
    "ALKIMIA": 0.0,
    "UNIMED": -0.47,
    "SIPHAT": 0.0,
    "TAWASOL GP HOLDING": -2.41,
    "SOTETEL": 0.0,
    "SOTRAPIL": 0.0,
    "ASSAD": -4.44,
    "STIP": 4.39,
    "TELNET HOLDING": 4.6,
    "AETECH": 0.0,
    "TUNISAIR": 0.0
  }
}