{
  "updated_at": "2026-03-13",
  "source": "physionomie_boursiere_20260313.pdf",
  "count": 76,
  "prices": {
    "TUNINDEX": 15499.14,
    "BIAT": 142.3,
    "ATTIJARI BANK": 74.0,
    "AMEN BANK": 60.7,
    "BT": 7.5,
    "BNA": 14.75,
    "UIB": 28.0,
    "UBCI": 37.6,
    "STB": 4.12,
    "BH BANK": 10.19,
    "ATB": 3.75,
    "WIFACK INT BANK": 7.65,
    "BTE": 6.05,
    "POULINA GP HOLDING": 23.95,
    "SFBT": 13.14,
    "DELICE HOLDING": 15.89,
    "LAND'OR": 15.63,
    "ARTES": 15.0,
    "ENNAKL AUTOMOBILES": 17.5,
    "CITY CARS": 25.83,
    "SMART TUNISIE": 20.75,
    "MONOPRIX": 7.1,
    "MAGASIN GENERAL": 10.36,
    "SOTUMAG": 9.65,
    "STA": 58.99,
    "UADH": 0.44,
    "CELLCOM": 2.53,
    "BNA ASSURANCES": 261.6,
    "STAR": 63.81,
    "TUNIS RE": 14.6,
    "ASSUR MAGHREBIA": 61.04,
    "ASTREE": 45.41,
    "ASSU MAGHREBIA VIE": 8.21,
    "BH ASSURANCE": 65.5,
    "TUNISIE LEASING F": 41.3,
    "SPDIT-SICAF": 14.0,
    "ATL": 8.21,
    "CIL": 33.9,
    "ATTIJARI LEASING": 33.5,
    "HANNIBAL LEASE": 7.25,
    "BEST LEASE": 2.27,
    "PLAC. TSIE-SICAF": 41.81,
    "TUNINVEST-SICAR": 41.45,
    "BH LEASING": 3.97,
    "ONE TECH HOLDING": 8.66,
    "SOTUVER": 16.84,
    "SIAME": 3.2,
    "SAH": 14.0,
    "EURO-CYCLES": 11.76,
    "ATELIER MEUBLE INT": 4.82,
    "OFFICEPLAST": 1.96,
    "NEW BODY LINE": 3.88,
    "CARTHAGE CEMENT": 1.98,
    "MPBS": 8.2,
    "SOTEMAIL": 3.0,
    "SITS": 3.88,
    "SIMPAR": 34.4,
    "SOMOCER": 0.6,
    "CIMENTS DE BIZERTE": 0.47,
    "ESSOUKNA": 3.77,
    "SANIMED": 0.7,
    "TPR": 13.52,
    "SOTIPAPIER": 2.64,
    "AIR LIQUIDE TSIE": 173.89,
    "ICF": 78.5,
    "ALKIMIA": 12.41,
    "UNIMED": 8.81,
    "SIPHAT": 4.66,
    "TAWASOL GP HOLDING": 0.83,
    "SOTETEL": 6.6,
    "SOTRAPIL": 26.2,
    "ASSAD": 2.96,
    "STIP": 7.16,
    "TELNET HOLDING": 6.4,
    "AETECH": 0.41,
    "TUNISAIR": 0.34
  },
  "variations": {
    "BIAT": -2.53,
    "ATTIJARI BANK": -1.33,
    "AMEN BANK": -0.96,
    "BT": 2.04,
    "BNA": -0.87,
    "UIB": 0.0,
    "UBCI": 0.27,
    "STB": -2.83,
    "BH BANK": 1.49,
    "ATB": 0.27,
    "WIFACK INT BANK": 0.66,
    "BTE": 0.0,
    "POULINA GP HOLDING": -0.21,
    "SFBT": 0.0,
    "DELICE HOLDING": 0.57,
    "LAND'OR": -0.06,
    "ARTES": -0.79,
    "ENNAKL AUTOMOBILES": 0.57,
    "CITY CARS": -0.65,
    "SMART TUNISIE": 0.73,
    "MONOPRIX": 4.41,
    "MAGASIN GENERAL": 0.0,
    "SOTUMAG": -1.03,
    "STA": -1.65,
    "UADH": 0.0,
    "CELLCOM": 0.4,
    "BNA ASSURANCES": -6.01,
    "STAR": 0.49,
    "TUNIS RE": -1.35,
    "ASSUR MAGHREBIA": 2.59,
    "ASTREE": -4.48,
    "ASSU MAGHREBIA VIE": 0.24,
    "BH ASSURANCE": 0.0,
    "TUNISIE LEASING F": 0.0,
    "SPDIT-SICAF": 0.0,
    "ATL": 0.12,
    "CIL": -0.29,
    "ATTIJARI LEASING": 0.0,
    "HANNIBAL LEASE": 0.0,
    "BEST LEASE": 0.0,
    "PLAC. TSIE-SICAF": 0.0,
    "TUNINVEST-SICAR": 0.85,
    "BH LEASING": 4.47,
    "ONE TECH HOLDING": -0.35,
    "SOTUVER": 0.0,
    "SIAME": 1.91,
    "SAH": -0.43,
    "EURO-CYCLES": 0.0,
    "ATELIER MEUBLE INT": -0.41,
    "OFFICEPLAST": 0.0,
    "NEW BODY LINE": -2.02,
    "CARTHAGE CEMENT": 0.51,
    "MPBS": 0.0,
    "SOTEMAIL": 0.0,
    "SITS": 0.0,
    "SIMPAR": 0.0,
    "SOMOCER": -1.64,
    "CIMENTS DE BIZERTE": 0.0,
    "ESSOUKNA": 1.89,
    "SANIMED": 4.48,
    "TPR": -0.59,
    "SOTIPAPIER": 0.0,
    "AIR LIQUIDE TSIE": 0.01,
    "ICF": 0.64,
    "ALKIMIA": 0.0,
    "UNIMED": -3.72,
    "SIPHAT": 0.0,
    "TAWASOL GP HOLDING": 0.0,
    "SOTETEL": 0.0,
    "SOTRAPIL": 0.77,
    "ASSAD": -0.34,
    "STIP": 4.37,
    "TELNET HOLDING": 0.16,
    "AETECH": 0.0,
    "TUNISAIR": 0.0
  }
}